example.py
tests.py
AnyArgs/AnyArgs.py
AnyArgs/Group.py
AnyArgs/__init__.py
AnyArgs/argtypes.py
AnyArgs-0.1.1.dist-info/METADATA
AnyArgs-0.1.1.dist-info/WHEEL
AnyArgs-0.1.1.dist-info/top_level.txt
AnyArgs-0.1.1.dist-info/RECORD
