Metadata-Version: 2.1
Name: AnyArgs
Version: 0.1.1
Summary: Turn all the markdown files in your repos into one big, divio structrured documentation
Author-email: Denperidge <denperidge@gmail.com>
Project-URL: Homepage, https://github.com/Denperidge-Redpencil/AnyArgs
Project-URL: Bug Tracker, https://github.com/Denperidge-Redpencil/AnyArgs/issues
Classifier: Development Status :: 3 - Alpha
Classifier: Intended Audience :: Information Technology
Classifier: License :: OSI Approved :: MIT License
Classifier: Operating System :: OS Independent
Classifier: Programming Language :: Python :: 3
Classifier: Topic :: Software Development
Requires-Python: >=3.7
